drf_stripe/__init__.py
drf_stripe/admin.py
drf_stripe/apps.py
drf_stripe/models.py
drf_stripe/serializers.py
drf_stripe/settings.py
drf_stripe/urls.py
drf_stripe/views.py
drf_stripe/management/__init__.py
drf_stripe/management/commands/__init__.py
drf_stripe/management/commands/pull_stripe.py
drf_stripe/management/commands/update_stripe_customers.py
drf_stripe/management/commands/update_stripe_products.py
drf_stripe/management/commands/update_stripe_subscriptions.py
drf_stripe/migrations/0001_initial.py
drf_stripe/migrations/0002_alter_feature_description_alter_price_freq_and_more.py
drf_stripe/migrations/0003_price_currency.py
drf_stripe/migrations/__init__.py
drf_stripe/stripe_api/__init__.py
drf_stripe/stripe_api/api.py
drf_stripe/stripe_api/checkout.py
drf_stripe/stripe_api/customer_portal.py
drf_stripe/stripe_api/customers.py
drf_stripe/stripe_api/products.py
drf_stripe/stripe_api/subscriptions.py
drf_stripe/stripe_models/__init__.py
drf_stripe/stripe_models/currency.py
drf_stripe/stripe_models/customer.py
drf_stripe/stripe_models/event.py
drf_stripe/stripe_models/invoice.py
drf_stripe/stripe_models/price.py
drf_stripe/stripe_models/product.py
drf_stripe/stripe_models/subscription.py
drf_stripe/stripe_webhooks/__init__.py
drf_stripe/stripe_webhooks/customer_subscription.py
drf_stripe/stripe_webhooks/handler.py
drf_stripe/stripe_webhooks/price.py
drf_stripe/stripe_webhooks/product.py
tests/api/__init__.py
tests/api/test_update_customers.py
tests/api/test_update_products_prices.py
tests/api/test_update_subscriptions.py
tests/webhook/__init__.py
tests/webhook/test_event_product_price.py
tests/webhook/test_subscription.py
drf_stripe_subscription-1.2.2.dist-info/LICENSE
drf_stripe_subscription-1.2.2.dist-info/METADATA
drf_stripe_subscription-1.2.2.dist-info/WHEEL
drf_stripe_subscription-1.2.2.dist-info/top_level.txt
drf_stripe_subscription-1.2.2.dist-info/RECORD
